SafeDriver/__init__.py
SafeDriver/drivers.py
SafeDriver-1.2.8.dist-info/LICENSE.txt
SafeDriver-1.2.8.dist-info/METADATA
SafeDriver-1.2.8.dist-info/WHEEL
SafeDriver-1.2.8.dist-info/top_level.txt
SafeDriver-1.2.8.dist-info/RECORD
