Metadata-Version: 2.1
Name: SafeDriver
Version: 1.2.8
Summary: 自动检测并更新driver文件，提高selenium代码的稳定性
Home-page: 
Author: 测码范晔
Author-email: 1538379200@qq.com
License: UNKNOWN
Platform: UNKNOWN
Classifier: Programming Language :: Python :: 3
Classifier: License :: OSI Approved :: MIT License
Classifier: Operating System :: OS Independent
License-File: LICENSE.txt
Requires-Dist: selenium
Requires-Dist: bs4
Requires-Dist: requests
Requires-Dist: lxml
